AUTHORS.rst
CHANGES.rst
LICENSE
MANIFEST.in
README.rst
setup.py
EnvelopesWithSMTPS.egg-info/PKG-INFO
EnvelopesWithSMTPS.egg-info/SOURCES.txt
EnvelopesWithSMTPS.egg-info/dependency_links.txt
EnvelopesWithSMTPS.egg-info/not-zip-safe
EnvelopesWithSMTPS.egg-info/top_level.txt
docs/.gitignore
docs/Makefile
docs/conf.py
docs/index.rst
docs/make.bat
docs/api/conn.rst
docs/api/connstack.rst
docs/api/envelope.rst
docs/examples/celery.rst
docs/examples/flask.rst
envelopes/__init__.py
envelopes/compat.py
envelopes/conn.py
envelopes/connstack.py
envelopes/envelope.py
envelopes/local.py
examples/__init__.py
examples/example_celery.py
examples/example_flask.py
lib/__init__.py
lib/testing.py
tests/test_conn.py
tests/test_envelope.py