Metadata-Version: 1.1
Name: EnvelopesWithSMTPS
Version: 0.4
Summary: Mailing for human beings
Home-page: http://tomekwojcik.github.io/envelopes/
Author: b'Tomasz W\xc3\xb3jcik'
Author-email: tomek@bthlabs.pl
License: https://github.com/tomekwojcik/envelopes/blob/master/LICENSE
Download-URL: http://github.com/tomekwojcik/envelopes/tarball/v0.4
Platform: any
Classifier: Development Status :: 4 - Beta
Classifier: Environment :: Other Environment
Classifier: Intended Audience :: Developers
Classifier: License :: OSI Approved :: MIT License
Classifier: Operating System :: OS Independent
Classifier: Programming Language :: Python :: 2
Classifier: Programming Language :: Python :: 2.6
Classifier: Programming Language :: Python :: 2.7
Classifier: Programming Language :: Python :: 3
Classifier: Programming Language :: Python :: 3.3
Classifier: Topic :: Software Development :: Libraries :: Python Modules
